pytempl/__init__.py
pytempl/base.py
pytempl/errors.py
pytempl/safe_string.py
pytempl/utils.py
pytempl/plugins/__init__.py
pytempl/plugins/alpinejs/__init__.py
pytempl/plugins/htmx/__init__.py
pytempl/plugins/htmx/_base.py
pytempl/plugins/tailwindcss/__init__.py
pytempl/tags/__init__.py
pytempl/tags/html/__init__.py
pytempl/tags/html/_base.py
pytempl/tags/html/a.py
pytempl/tags/html/abbr.py
pytempl/tags/html/address.py
pytempl/tags/html/area.py
pytempl/tags/html/article.py
pytempl/tags/html/aside.py
pytempl/tags/html/audio.py
pytempl/tags/html/b.py
pytempl/tags/html/base.py
pytempl/tags/html/bdi.py
pytempl/tags/html/bdo.py
pytempl/tags/html/blockquote.py
pytempl/tags/html/body.py
pytempl/tags/html/br.py
pytempl/tags/html/button.py
pytempl/tags/html/canvas.py
pytempl/tags/html/caption.py
pytempl/tags/html/cite.py
pytempl/tags/html/code.py
pytempl/tags/html/col.py
pytempl/tags/html/colgroup.py
pytempl/tags/html/data.py
pytempl/tags/html/datalist.py
pytempl/tags/html/dd.py
pytempl/tags/html/del_.py
pytempl/tags/html/details.py
pytempl/tags/html/dfn.py
pytempl/tags/html/dialog.py
pytempl/tags/html/div.py
pytempl/tags/html/dl.py
pytempl/tags/html/dt.py
pytempl/tags/html/em.py
pytempl/tags/html/embed.py
pytempl/tags/html/fieldset.py
pytempl/tags/html/figcaption.py
pytempl/tags/html/figure.py
pytempl/tags/html/footer.py
pytempl/tags/html/form.py
pytempl/tags/html/h.py
pytempl/tags/html/head.py
pytempl/tags/html/header.py
pytempl/tags/html/hgroup.py
pytempl/tags/html/hr.py
pytempl/tags/html/html.py
pytempl/tags/html/i.py
pytempl/tags/html/iframe.py
pytempl/tags/html/img.py
pytempl/tags/html/input.py
pytempl/tags/html/ins.py
pytempl/tags/html/kbd.py
pytempl/tags/html/label.py
pytempl/tags/html/legend.py
pytempl/tags/html/li.py
pytempl/tags/html/link.py
pytempl/tags/html/main.py
pytempl/tags/html/map.py
pytempl/tags/html/mark.py
pytempl/tags/html/menu.py
pytempl/tags/html/meta.py
pytempl/tags/html/meter.py
pytempl/tags/html/nav.py
pytempl/tags/html/noscript.py
pytempl-0.2.10.dist-info/METADATA
pytempl-0.2.10.dist-info/WHEEL
pytempl-0.2.10.dist-info/RECORD
