Metadata-Version: 2.4
Name: pytempl
Version: 0.2.10
Summary: DSL for writing HTML user interfaces in Python.
Project-URL: homepage, https://github.com/aether-py/pytempl
Project-URL: repository, https://github.com/aether-py/pytempl
Project-URL: documentation, https://github.com/aether-py/pytempl
Author-email: Saurabh Ghanekar <ghanekarsaurabh8@gmail.com>
License-Expression: BSD-2-Clause
Classifier: Operating System :: OS Independent
Classifier: Programming Language :: Python :: 3
Requires-Python: >=3.10
Requires-Dist: pydantic>=2.10
Requires-Dist: typing-extensions>=4
